CHANGELOG.txt
LICENSE.txt
MANIFEST.in
README.txt
__init__.py
setup.py
OtoKotolashvili.egg-info/PKG-INFO
OtoKotolashvili.egg-info/SOURCES.txt
OtoKotolashvili.egg-info/dependency_links.txt
OtoKotolashvili.egg-info/top_level.txt
yamari/Lib/site-packages/_virtualenv.py
yamari/Lib/site-packages/_distutils_hack/__init__.py
yamari/Lib/site-packages/_distutils_hack/override.py
yamari/Lib/site-packages/pip/__init__.py
yamari/Lib/site-packages/pip/__main__.py
yamari/Lib/site-packages/pip/__pip-runner__.py
yamari/Lib/site-packages/pip-22.3.1.dist-info/LICENSE.txt
yamari/Lib/site-packages/pip-22.3.1.dist-info/entry_points.txt
yamari/Lib/site-packages/pip-22.3.1.dist-info/top_level.txt
yamari/Lib/site-packages/pip/_internal/__init__.py
yamari/Lib/site-packages/pip/_internal/build_env.py
yamari/Lib/site-packages/pip/_internal/cache.py
yamari/Lib/site-packages/pip/_internal/configuration.py
yamari/Lib/site-packages/pip/_internal/exceptions.py
yamari/Lib/site-packages/pip/_internal/main.py
yamari/Lib/site-packages/pip/_internal/pyproject.py
yamari/Lib/site-packages/pip/_internal/self_outdated_check.py
yamari/Lib/site-packages/pip/_internal/wheel_builder.py
yamari/Lib/site-packages/pip/_internal/cli/__init__.py
yamari/Lib/site-packages/pip/_internal/cli/autocompletion.py
yamari/Lib/site-packages/pip/_internal/cli/base_command.py
yamari/Lib/site-packages/pip/_internal/cli/cmdoptions.py
yamari/Lib/site-packages/pip/_internal/cli/command_context.py
yamari/Lib/site-packages/pip/_internal/cli/main.py
yamari/Lib/site-packages/pip/_internal/cli/main_parser.py
yamari/Lib/site-packages/pip/_internal/cli/parser.py
yamari/Lib/site-packages/pip/_internal/cli/progress_bars.py
yamari/Lib/site-packages/pip/_internal/cli/req_command.py
yamari/Lib/site-packages/pip/_internal/cli/spinners.py
yamari/Lib/site-packages/pip/_internal/cli/status_codes.py
yamari/Lib/site-packages/pip/_internal/commands/__init__.py
yamari/Lib/site-packages/pip/_internal/commands/cache.py
yamari/Lib/site-packages/pip/_internal/commands/check.py
yamari/Lib/site-packages/pip/_internal/commands/completion.py
yamari/Lib/site-packages/pip/_internal/commands/configuration.py
yamari/Lib/site-packages/pip/_internal/commands/debug.py
yamari/Lib/site-packages/pip/_internal/commands/download.py
yamari/Lib/site-packages/pip/_internal/commands/freeze.py
yamari/Lib/site-packages/setuptools-65.5.1.dist-info/entry_points.txt
yamari/Lib/site-packages/setuptools-65.5.1.dist-info/top_level.txt
yamari/Lib/site-packages/wheel-0.38.4.dist-info/LICENSE.txt
yamari/Lib/site-packages/wheel-0.38.4.dist-info/entry_points.txt
yamari/Lib/site-packages/wheel-0.38.4.dist-info/top_level.txt
